{"op":"ticket.create","value":{"assignee":"none","body":"## Summary\n\nUpgrade `lucide-react` from 1.17.0 to 1.21.0 in the packages that declare it.\n\n## Affected manifests\n\n- `packages/desktop/package.json`\n- `packages/ui/package.json`\n\n## Rationale\n\n`pnpm outdated --recursive --format json` reports a newer minor release. This should be low risk, but icon packages can occasionally rename or adjust exports, so build verification is enough unless visual changes are obvious.\n\n## Verification\n\n- Run `pnpm --filter @cycle/desktop build`.\n- Run `pnpm --filter @cycle/ui storybook:build`.\n- Smoke test the desktop shell for missing icons.","bodyFormat":"markdown","createdBy":"robert.pitt-foodhub.com","frontmatter":{"createdAt":"2026-06-22T10:54:29.522Z","createdBy":{"email":"robert.pitt@foodhub.com","name":"Robert PItt","type":"human"},"id":"UKN-CYYTR","labels":["improvement"],"priority":"low","status":"backlog","title":"Upgrade lucide-react to 1.21.0","type":"task","updatedAt":"2026-06-22T10:54:29.522Z"},"id":"UKN-CYYTR","labels":["improvement"],"parent":"none","priority":"low","schemaVersion":1,"status":"backlog","title":"Upgrade lucide-react to 1.21.0","type":"task","updatedDate":"2026-06-22"}}