{"op":"ticket.create","value":{"assignee":"none","body":"Found during a follow-up static issue scan of the Cycle codebase.\n\nProblem:\nThe desktop renderer accepts API tokens from query/hash parameters and persists them into `window.localStorage`. Bearer tokens in URLs can leak via history, logs, screenshots, and referrers; persisting them in localStorage also makes them long-lived and available to any renderer script running in that origin.\n\nEvidence:\n- `packages/desktop/src/renderer/lib/cycleApiClient.ts:136-149` reads `cycleApiToken` / `apiToken` from `window.location.search` and hash query params.\n- `packages/desktop/src/renderer/lib/cycleApiClient.ts:151-152` writes the token to `API_TOKEN_STORAGE_KEY` in `window.localStorage`.\n- `packages/desktop/src/renderer/lib/cycleApiClient.ts:160-169` reads that stored token back for later requests.\n- `packages/desktop/src/renderer/lib/cycleApiClient.ts:293-297` sends the stored token as the bearer Authorization header.\n\nSuggested remediation:\n- Do not persist bearer tokens supplied via URL params. Treat URL-provided tokens as one-shot/session-scoped at most.\n- Prefer the secure preload bridge (`getApiConnection`) for desktop runtime tokens.\n- If browser/dev override tokens are still required, store them in memory or sessionStorage behind explicit dev-only handling and document the risk.\n- Provide a migration/cleanup path that removes existing `cycle.api.token` localStorage entries.\n\nAcceptance criteria:\n- Query/hash token values are not written to localStorage.\n- Existing localStorage token entries are ignored or cleared unless explicitly supported by a documented dev-only mode.\n- API discovery tests cover URL token handling without persistent storage.","bodyFormat":"markdown","createdBy":"robertpitt1988-gmail.com","frontmatter":{"createdAt":"2026-06-19T00:38:29.621Z","createdBy":{"email":"robertpitt1988@gmail.com","name":"Robert PItt 2","type":"human"},"id":"UKN-4ZHKM","priority":"high","status":"backlog","title":"Stop persisting API bearer tokens from URL params into localStorage","type":"bug","updatedAt":"2026-06-19T00:38:29.621Z"},"id":"UKN-4ZHKM","parent":"none","priority":"high","schemaVersion":1,"status":"backlog","title":"Stop persisting API bearer tokens from URL params into localStorage","type":"bug","updatedDate":"2026-06-19"}}