{"op":"ticket.create","value":{"assignee":"none","body":"## Context\n\nAgent task endpoints can create, list, read, cancel, retry, and stream task events, but users need a product surface that explains what agents are doing.\n\n## Outcome\n\nA dashboard shows queued, running, waiting, failed, canceled, and completed agent tasks across repositories and tickets.\n\n## Acceptance criteria\n\n- Dashboard lists active and recent tasks with repository, ticket, provider, workflow, status, age, and latest event.\n- Users can filter by repository, ticket, provider, and status.\n- Task detail links back to the related ticket and run artifacts.\n- Empty and failure states explain missing providers, disabled providers, or backend failures.\n- API query behavior and renderer mapping are covered by tests.","bodyFormat":"markdown","createdBy":"robert.pitt-foodhub.com","frontmatter":{"createdAt":"2026-07-10T12:41:32.488Z","createdBy":{"email":"robert.pitt@foodhub.com","name":"Robert Pitt","type":"human"},"id":"UKN-F00JU","labels":["feature"],"parent":"UKN-7WO7S","priority":"high","status":"backlog","title":"Build an agent task queue and run dashboard","type":"feature","updatedAt":"2026-07-10T12:41:32.488Z"},"id":"UKN-F00JU","labels":["feature"],"parent":"UKN-7WO7S","priority":"high","schemaVersion":1,"status":"backlog","title":"Build an agent task queue and run dashboard","type":"feature","updatedDate":"2026-07-10"}}