{"op":"ticket.create","value":{"assignee":"none","body":"## Cleanup candidate\n\nTheme, density, API host, and repository commit-style literals are defined separately in desktop app config, API response schemas, and API runtime settings types.\n\n## Evidence\n\n- Desktop config schemas: `packages/desktop/src/shared/AppConfig.ts`\n  - `ThemePreference = Schema.Literals([\"light\", \"dark\", \"system\"])`\n  - `InterfaceDensity = Schema.Literals([\"compact\", \"spacious\"])`\n  - API host literals\n  - `RepositoryCommitStyle = Schema.Literals([\"descriptive\", \"compact\"])`\n- API HTTP schemas: `packages/api/src/http/schemas/AppConfigResourceEnvelope.ts`\n  - same `ThemePreference`, `InterfaceDensity`, API host literals, and `RepositoryCommitStyle` shapes.\n- API runtime TypeScript-only aliases: `packages/api/src/http/runtime/CycleApiRuntime.ts`\n  - `LocalSettingsThemePreference`\n  - `LocalSettingsInterfaceDensity`\n  - `LocalSettingsRepositoryCommitStyle`\n\n## Suggested approach\n\nCreate or reuse canonical app-settings schemas/types that both desktop and API can import. Prefer schema-derived types over TypeScript-only literal unions at process boundaries, and derive API payload/output schemas from the shared source where practical.\n\n## Acceptance criteria\n\n- Preference and commit-style literal sets are defined in one canonical module.\n- API payload/output schemas and runtime provider types are schema-derived or import the same canonical types.\n- Existing config parsing, HTTP payload validation, and desktop settings mutations remain compatible.","bodyFormat":"markdown","createdBy":"robert.pitt-foodhub.com","frontmatter":{"createdAt":"2026-07-05T18:24:12.218Z","createdBy":{"email":"robert.pitt@foodhub.com","name":"Robert Pitt","type":"human"},"id":"UKN-8X352","priority":"medium","status":"backlog","title":"Consolidate local settings preference types and schemas across desktop and API","type":"task","updatedAt":"2026-07-05T18:24:12.218Z"},"id":"UKN-8X352","parent":"none","priority":"medium","schemaVersion":1,"status":"backlog","title":"Consolidate local settings preference types and schemas across desktop and API","type":"task","updatedDate":"2026-07-05"}}